{
    "data" :  {
    "name": "Tofu Causes Deforestation",
    "permalink" : "https://talkveganto.me/en/facts/tofu-causes-deforestation/"
}
 ,
    "languages": [
        
        {
          "languageShortCode": "en",
          "languageName": "English"
        }
      
        , 
        {
          "languageShortCode": "fr",
          "languageName": "Français"
        }
      
    ],
    "languageName": "English",
    "languageShortCode": "en",
    "date": "2019-10-01T18:59:51.368177322Z"
}
