{
    "data" :  {
    "name": "Animal Life Expectancy",
    "permalink" : "https://talkveganto.me/en/vegan-statistics/animal-life-expectancy/"
}
 ,
    "languages": [
        
        {
          "languageShortCode": "en",
          "languageName": "English"
        }
      
        , 
        {
          "languageShortCode": "fr",
          "languageName": "French"
        }
      
    ],
    "languageName": "English",
    "languageShortCode": "en",
    "date": "2019-05-28T21:40:58.237630554Z"
}
