{
    "data" :  {
    "name": "Animals Are Slaughtered Humanely",
    "permalink" : "https://talkveganto.me/en/anti-vegan/animals-are-slaughtered-humanely/"
}
 ,
    "languages": [
        
        {
          "languageShortCode": "en",
          "languageName": "English"
        }
      
        , 
        {
          "languageShortCode": "fr",
          "languageName": "French"
        }
      
    ],
    "languageName": "English",
    "languageShortCode": "en",
    "date": "2019-07-11T14:56:22.404051171Z"
}
